blue_crab-0.4.0.dist-info/licenses/LICENSE
src/__init__.py
src/_version.py
src/blue_crab.py
blue_crab-0.4.0.dist-info/METADATA
blue_crab-0.4.0.dist-info/WHEEL
blue_crab-0.4.0.dist-info/entry_points.txt
blue_crab-0.4.0.dist-info/top_level.txt
blue_crab-0.4.0.dist-info/RECORD
