Metadata-Version: 2.4
Name: blue-crab
Version: 0.4.0
Summary: blue-crab: A Slow5/Blow5 <-> Pod5 converter
Home-page: https://github.com/Psy-Fer/blue-crab
Author: James Ferguson, Hasindu Gamaarachchi
Author-email: j.ferguson@garvan.org.au
Maintainer: James Ferguson
Maintainer-email: j.ferguson@garvan.org.au
License: MIT
Keywords: nanopore,slow5,pod5
Classifier: Development Status :: 5 - Production/Stable
Classifier: Programming Language :: Python :: 3
Classifier: License :: OSI Approved :: MIT License
Classifier: Intended Audience :: Science/Research
Classifier: Topic :: Scientific/Engineering :: Bio-Informatics
Requires-Python: >=3.9
License-File: LICENSE
Requires-Dist: numpy
Requires-Dist: pyslow5>=1.3.0
Requires-Dist: pod5>=0.3.27
Dynamic: author
Dynamic: author-email
Dynamic: classifier
Dynamic: description
Dynamic: description-content-type
Dynamic: home-page
Dynamic: keywords
Dynamic: license
Dynamic: license-file
Dynamic: maintainer
Dynamic: maintainer-email
Dynamic: requires-dist
Dynamic: requires-python
Dynamic: summary
